[
  {
    "serviceId": "001",
    "serviceName": "Basic Plumbing Fix",
    "serviceImage": "/images/demo-img/chatterbox-thumb.jpeg",
    "providerEmail": "provider1@example.com",
    "providerName": "John Doe",
    "serviceProviderName": "John Doe",
    "serviceProviderImage": "https://img.daisyui.com/images/profile/demo/2@94.webp",
    "serviceLocation": "New York",
    "currentUserEmail": "user1@example.com",
    "currentUserName": "Alice Johnson",
    "serviceTakingDate": "2024-12-10",
    "specialInstruction": "Leaking sink needs repair",
    "price": "$150",
    "serviceStatus": "pending"
  },
  {
    "serviceId": "002",
    "serviceName": "Electrical Wiring Check",
    "serviceImage": "/images/demo-img/cli-browser-thumb.jpeg",
    "providerEmail": "provider2@example.com",
    "providerName": "Jane Smith",
    "serviceProviderName": "Jane Smith",
    "serviceProviderImage": "https://img.daisyui.com/images/profile/demo/2@94.webp",
    "serviceLocation": "Los Angeles",
    "currentUserEmail": "user2@example.com",
    "currentUserName": "Bob Green",
    "serviceTakingDate": "2024-12-15",
    "specialInstruction": "Check faulty wiring in the living room",
    "price": "$200",
    "serviceStatus": "pending"
  },
  {
    "serviceId": "003",
    "serviceName": "Ceiling Fan Installation",
    "serviceImage": "/images/demo-img/ctrl-enter-thumb.jpeg",
    "providerEmail": "provider3@example.com",
    "providerName": "Michael Lee",
    "serviceProviderName": "Michael Lee",
    "serviceProviderImage": "https://img.daisyui.com/images/profile/demo/2@94.webp",
    "serviceLocation": "Chicago",
    "currentUserEmail": "user3@example.com",
    "currentUserName": "Sara White",
    "serviceTakingDate": "2024-12-20",
    "specialInstruction": "Install fan in the master bedroom",
    "price": "$100",
    "serviceStatus": "pending"
  },
  {
    "serviceId": "004",
    "serviceName": "Kitchen Faucet Replacement",
    "serviceImage": "/images/demo-img/default-books-thumb.jpeg",
    "providerEmail": "provider4@example.com",
    "providerName": "David Brown",
    "serviceProviderName": "David Brown",
    "serviceProviderImage": "https://img.daisyui.com/images/profile/demo/2@94.webp",
    "serviceLocation": "Houston",
    "currentUserEmail": "user4@example.com",
    "currentUserName": "Chris Evans",
    "serviceTakingDate": "2024-12-12",
    "specialInstruction": "Replace old faucet with modern one",
    "price": "$180",
    "serviceStatus": "pending"
  },
  {
    "serviceId": "005",
    "serviceName": "Water Heater Repair",
    "serviceImage": "/images/demo-img/dropdowns-thumb.jpeg",
    "providerEmail": "provider5@example.com",
    "providerName": "Amy Williams",
    "serviceProviderName": "Amy Williams",
    "serviceProviderImage": "https://img.daisyui.com/images/profile/demo/2@94.webp",
    "serviceLocation": "Phoenix",
    "currentUserEmail": "user5@example.com",
    "currentUserName": "Paul Walker",
    "serviceTakingDate": "2024-12-14",
    "specialInstruction": "Heater not producing hot water",
    "price": "$250",
    "serviceStatus": "pending"
  },
  {
    "serviceId": "006",
    "serviceName": "Bathroom Tile Replacement",
    "serviceImage": "/images/demo-img/Editing_And_Deleting_-thumb.jpeg",
    "providerEmail": "provider6@example.com",
    "providerName": "James Johnson",
    "serviceProviderName": "James Johnson",
    "serviceProviderImage": "https://img.daisyui.com/images/profile/demo/2@94.webp",
    "serviceLocation": "San Diego",
    "currentUserEmail": "user6@example.com",
    "currentUserName": "Jessica Turner",
    "serviceTakingDate": "2024-12-18",
    "specialInstruction": "Replace cracked bathroom tiles",
    "price": "$300",
    "serviceStatus": "pending"
  },
  {
    "serviceId": "007",
    "serviceName": "Smoke Detector Installation",
    "serviceImage": "/images/demo-img/filament-adding-some-style-thumb.jpeg",
    "providerEmail": "provider7@example.com",
    "providerName": "Emily Davis",
    "serviceProviderName": "Emily Davis",
    "serviceProviderImage": "https://img.daisyui.com/images/profile/demo/2@94.webp",
    "serviceLocation": "Dallas",
    "currentUserEmail": "user7@example.com",
    "currentUserName": "David Kim",
    "serviceTakingDate": "2024-12-16",
    "specialInstruction": "Install detectors in all rooms",
    "price": "$90",
    "serviceStatus": "pending"
  },
  {
    "serviceId": "008",
    "serviceName": "Home Painting Service",
    "serviceImage": "/images/demo-img/filamentphp-shooting-lasers-at-the-moon-thumb.jpeg",
    "providerEmail": "provider8@example.com",
    "providerName": "Linda Clark",
    "serviceProviderName": "Linda Clark",
    "serviceProviderImage": "https://img.daisyui.com/images/profile/demo/2@94.webp",
    "serviceLocation": "Philadelphia",
    "currentUserEmail": "user8@example.com",
    "currentUserName": "Mark Stone",
    "serviceTakingDate": "2024-12-25",
    "specialInstruction": "Paint entire living room",
    "price": "$450",
    "serviceStatus": "pending"
  },
  {
    "serviceId": "009",
    "serviceName": "Carpet Cleaning Service",
    "serviceImage": "/images/demo-img/files-are-inside-the-computer-thumb.jpeg",
    "providerEmail": "provider9@example.com",
    "providerName": "Kevin Scott",
    "serviceProviderName": "Kevin Scott",
    "serviceProviderImage": "https://img.daisyui.com/images/profile/demo/2@94.webp",
    "serviceLocation": "San Antonio",
    "currentUserEmail": "user9@example.com",
    "currentUserName": "Nancy Cruz",
    "serviceTakingDate": "2024-12-22",
    "specialInstruction": "Deep clean all carpets in the house",
    "price": "$350",
    "serviceStatus": "pending"
  },
  {
    "serviceId": "010",
    "serviceName": "Door Lock Repair",
    "serviceImage": "/images/demo-img/fly-checkboxes-thumb.jpeg",
    "providerEmail": "provider10@example.com",
    "providerName": "Robert Miller",
    "serviceProviderName": "Robert Miller",
    "serviceProviderImage": "https://img.daisyui.com/images/profile/demo/2@94.webp",
    "serviceLocation": "Austin",
    "currentUserEmail": "user10@example.com",
    "currentUserName": "Rachel Carter",
    "serviceTakingDate": "2024-12-29",
    "specialInstruction": "Fix the front door lock",
    "price": "$100",
    "serviceStatus": "pending"
  },
  {
    "serviceId": "011",
    "serviceName": "Shower Head Installation",
    "serviceImage": "/images/demo-img/gold-custom-pulse-thumb.jpeg",
    "providerEmail": "provider11@example.com",
    "providerName": "Michael Wilson",
    "serviceProviderName": "Michael Wilson",
    "serviceProviderImage": "https://img.daisyui.com/images/profile/demo/2@94.webp",
    "serviceLocation": "Seattle",
    "currentUserEmail": "user11@example.com",
    "currentUserName": "Linda Brown",
    "serviceTakingDate": "2024-12-23",
    "specialInstruction": "Install rain shower head in bathroom",
    "price": "$120",
    "serviceStatus": "pending"
  },
  {
    "serviceId": "012",
    "serviceName": "Window Cleaning Service",
    "serviceImage": "/images/demo-img/incinerate-the-machines-thumb.jpeg",
    "providerEmail": "provider12@example.com",
    "providerName": "Sarah Lewis",
    "serviceProviderName": "Sarah Lewis",
    "serviceProviderImage": "https://img.daisyui.com/images/profile/demo/2@94.webp",
    "serviceLocation": "Denver",
    "currentUserEmail": "user12@example.com",
    "currentUserName": "James Roberts",
    "serviceTakingDate": "2024-12-11",
    "specialInstruction": "Clean windows on the second floor",
    "price": "$140",
    "serviceStatus": "pending"
  }
]